farfun/__init__.py
farfun-202307211121.dist-info/METADATA
farfun-202307211121.dist-info/WHEEL
farfun-202307211121.dist-info/top_level.txt
farfun-202307211121.dist-info/RECORD
