Metadata-Version: 2.1
Name: farfun
Version: 202307211121
Summary: farfun
Home-page: https://github.com/1007530194
Author: bingtao
Author-email: 1007530194@qq.com
